Workbook

Sheet 支出流水表
A1: 报销批次 | B1: 序号 | C1: 购买日期 | D1: 支出内容 | E1: 项目类别 | F1: 支出类别 | G1: 数量 | H1: 单价 | I1: 发票金额 | J1: 实际支出金额 | K1: 发票号码 | L1: 备注 | M1: 是否辰景发票 | N1: 姓名 | O1: 支付宝账号
A2: n | B2: 1 | E2: 步兵机器人 | F2: 机械标准件 | I2: 625 | K2: ="26952000000329742856" -> 26952000000329742856 | N2: 汤小圆 | O2: xxxxxxxxxxx
A3: n | B3: 2 | C3: 46047 | E3: 步兵机器人 | F3: 机械标准件 | I3: 83 | K3: ="26952000000514448236" -> 26952000000514448236 | N3: 汤小圆 | O3: xxxxxxxxxxx
A4: n | B4: 3 | E4: 步兵机器人 | F4: 机械标准件 | I4: 140 | K4: ="26342000001346323546" -> 26342000001346323546 | N4: 汤小圆 | O4: xxxxxxxxxxx
A5: n | B5: 4 | E5: 步兵机器人 | F5: 机械标准件 | I5: 35 | K5: ="26952000001840012831" -> 26952000001840012831 | N5: 汤小圆 | O5: xxxxxxxxxxx
A6: n | B6: 5 | E6: 步兵机器人 | F6: 机械标准件 | I6: 122.36 | K6: ="26132000001392424741" -> 26132000001392424741 | N6: 汤小圆 | O6: xxxxxxxxxxx
A7: n | B7: 6 | E7: 步兵机器人 | F7: 机械标准件 | I7: 25.2 | K7: ="26442000005155989331" -> 26442000005155989331 | N7: 汤小圆 | O7: xxxxxxxxxxx
A8: n | B8: 7 | E8: 步兵机器人 | F8: 机械标准件 | I8: 20.11 | K8: ="26342000001943349616" -> 26342000001943349616 | N8: 汤小圆 | O8: xxxxxxxxxxx
A9: n | B9: 8 | E9: 步兵机器人 | F9: 机械标准件 | I9: 900 | K9: ="26342000001946902186" -> 26342000001946902186 | N9: 汤小圆 | O9: xxxxxxxxxxx
A10: n | B10: 9 | C10: 46158 | E10: 步兵机器人 | F10: 机械标准件 | I10: 83.1 | K10: ="26312000003921089566" -> 26312000003921089566 | N10: 汤小圆 | O10: xxxxxxxxxxx
A11: n | B11: 10 | E11: 步兵机器人 | F11: 机械标准件 | I11: 35 | K11: ="26952000002606165071" -> 26952000002606165071 | N11: 汤小圆 | O11: xxxxxxxxxxx
A12: n | B12: 11 | E12: 步兵机器人 | F12: 机械标准件 | I12: 8.92 | K12: ="26322000005000205211" -> 26322000005000205211 | N12: 汤小圆 | O12: xxxxxxxxxxx
A13: n | B13: 12 | E13: 步兵机器人 | F13: 机械标准件 | I13: 143.2 | K13: ="26952000002615721421" -> 26952000002615721421 | N13: 汤小圆 | O13: xxxxxxxxxxx
A14: n | B14: 13 | E14: 步兵机器人 | F14: 机械标准件 | I14: 176 | K14: ="26332000005317959991" -> 26332000005317959991 | N14: 汤小圆 | O14: xxxxxxxxxxx
A15: n | B15: 14 | C15: 46144 | E15: 步兵机器人 | F15: 机械标准件 | I15: 84 | K15: ="26322000005034447061" -> 26322000005034447061 | N15: 汤小圆 | O15: xxxxxxxxxxx
A16: n | B16: 15 | E16: 步兵机器人 | F16: 机械标准件 | I16: 55.7 | K16: ="26372000002993965696" -> 26372000002993965696 | N16: 汤小圆 | O16: xxxxxxxxxxx
A17: n | B17: 16 | E17: 步兵机器人 | F17: 机械标准件 | I17: 86 | K17: ="26322000005092363651" -> 26322000005092363651 | N17: 汤小圆 | O17: xxxxxxxxxxx
A18: n | B18: 17 | E18: 步兵机器人 | F18: 机械标准件 | I18: 36.94 | K18: ="26342000002002016881" -> 26342000002002016881 | N18: 汤小圆 | O18: xxxxxxxxxxx
A19: n | B19: 18 | C19: 46170 | E19: 步兵机器人 | F19: 机械标准件 | I19: 13.64 | K19: ="26342000002001430366" -> 26342000002001430366 | N19: 汤小圆 | O19: xxxxxxxxxxx
A20: n | B20: 19 | E20: 步兵机器人 | F20: 机械标准件 | I20: 20.61 | K20: ="26342000002001825046" -> 26342000002001825046 | N20: 汤小圆 | O20: xxxxxxxxxxx
A21: n | B21: 20 | E21: 步兵机器人 | F21: 机械标准件 | I21: 30.18 | K21: ="26342000002001121036" -> 26342000002001121036 | N21: 汤小圆 | O21: xxxxxxxxxxx
A22: n | B22: 21 | E22: 步兵机器人 | F22: 机械标准件 | I22: 920 | K22: ="26342000002002171591" -> 26342000002002171591 | N22: 汤小圆 | O22: xxxxxxxxxxx
A23: n | B23: 22 | C23: 46158 | E23: 步兵机器人 | F23: 机械标准件 | I23: 39.83 | K23: ="26342000002001431176" -> 26342000002001431176 | N23: 汤小圆 | O23: xxxxxxxxxxx
A24: n | B24: 23 | E24: 步兵机器人 | F24: 机械标准件 | I24: 13.62 | K24: ="26342000002002159006" -> 26342000002002159006 | N24: 汤小圆 | O24: xxxxxxxxxxx
A25: n | B25: 24 | E25: 步兵机器人 | F25: 机械标准件 | I25: 31.3 | K25: ="26342000002001678496" -> 26342000002001678496 | N25: 汤小圆 | O25: xxxxxxxxxxx
A26: n | B26: 25 | C26: 46161 | E26: 步兵机器人 | F26: 机械标准件 | I26: 19.17 | K26: ="26342000002012555956" -> 26342000002012555956 | N26: 汤小圆 | O26: xxxxxxxxxxx
A27: n | B27: 26 | C27: 46116 | E27: 差旅 | F27: 差旅费 | I27: 14.54 | K27: ="26127000000323688030" -> 26127000000323688030 | N27: 汤小圆 | O27: xxxxxxxxxxx
A28: n | B28: 27 | C28: 46014 | E28: 差旅 | F28: 差旅费 | I28: 178.5 | K28: ="26337000000614408522" -> 26337000000614408522 | N28: 汤小圆 | O28: xxxxxxxxxxx
A29: n | B29: 28 | N29: 汤小圆 | O29: xxxxxxxxxxx
A30: n | B30: 29 | N30: 汤小圆 | O30: xxxxxxxxxxx
A31: n | B31: 30 | N31: 汤小圆 | O31: xxxxxxxxxxx

Sheet 分类统计
A1: 项目类别 | B1: 合计 | C1: 支出类别 | D1: 合计
A2: 步兵机器人 | B2: =SUMIF(支出流水表!$E$2:$E$1999,分类统计!A2,支出流水表!$J$2:$J$1999) -> 0 | C2: 车&铣 | D2: =SUMIF(支出流水表!$F$2:$F$1999,分类统计!C2,支出流水表!$J$2:$J$1999) -> 0
A3: 工程机器人 | B3: =SUMIF(支出流水表!$E$2:$E$1999,分类统计!A3,支出流水表!$J$2:$J$1999) -> 0 | C3: 钣金 | D3: =SUMIF(支出流水表!$F$2:$F$479,分类统计!C3,支出流水表!$J$2:$J$479) -> 0
A4: 英雄机器人 | B4: =SUMIF(支出流水表!$E$2:$E$1999,分类统计!A4,支出流水表!$J$2:$J$1999) -> 0 | C4: 2D雕刻 | D4: =SUMIF(支出流水表!$F$2:$F$479,分类统计!C4,支出流水表!$J$2:$J$479) -> 0
A5: 哨兵机器人 | B5: =SUMIF(支出流水表!$E$2:$E$1999,分类统计!A5,支出流水表!$J$2:$J$1999) -> 0 | C5: 3D打印 | D5: =SUMIF(支出流水表!$F$2:$F$479,分类统计!C5,支出流水表!$J$2:$J$479) -> 0
A6: 空中机器人 | B6: =SUMIF(支出流水表!$E$2:$E$1999,分类统计!A6,支出流水表!$J$2:$J$1999) -> 0 | C6: 型材焊接 | D6: =SUMIF(支出流水表!$F$2:$F$479,分类统计!C6,支出流水表!$J$2:$J$479) -> 0
A7: 多机器人共用 | B7: =SUMIF(支出流水表!$E$2:$E$1999,分类统计!A7,支出流水表!$J$2:$J$1999) -> 0 | C7: 其他机械定制件 | D7: =SUMIF(支出流水表!$F$2:$F$479,分类统计!C7,支出流水表!$J$2:$J$479) -> 0
A8: 飞镖 | B8: =SUMIF(支出流水表!$E$2:$E$1999,分类统计!A8,支出流水表!$J$2:$J$1999) -> 0 | C8: 机械标准件 | D8: =SUMIF(支出流水表!$F$2:$F$479,分类统计!C8,支出流水表!$J$2:$J$479) -> 0
A9: 雷达 | B9: =SUMIF(支出流水表!$E$2:$E$1999,分类统计!A9,支出流水表!$J$2:$J$1999) -> 0 | C9: 机械工具 | D9: =SUMIF(支出流水表!$F$2:$F$479,分类统计!C9,支出流水表!$J$2:$J$479) -> 0
A10: 差旅 | B10: =SUMIF(支出流水表!$E$2:$E$1999,分类统计!A10,支出流水表!$J$2:$J$1999) -> 0 | C10: 维修费 | D10: =SUMIF(支出流水表!$F$2:$F$479,分类统计!C10,支出流水表!$J$2:$J$479) -> 0
A11: 其他（运营等） | B11: =SUMIF(支出流水表!$E$2:$E$1999,分类统计!A11,支出流水表!$J$2:$J$1999) -> 0 | C11: 电控元件 | D11: =SUMIF(支出流水表!$F$2:$F$479,分类统计!C11,支出流水表!$J$2:$J$479) -> 0
A12: 合计 | B12: =SUM(B2:B11) -> 0 | C12: PCB加工 | D12: =SUMIF(支出流水表!$F$2:$F$479,分类统计!C12,支出流水表!$J$2:$J$479) -> 0
C13: 电控线材 | D13: =SUMIF(支出流水表!$F$2:$F$479,分类统计!C13,支出流水表!$J$2:$J$479) -> 0
C14: 电控工具 | D14: =SUMIF(支出流水表!$F$2:$F$479,分类统计!C14,支出流水表!$J$2:$J$479) -> 0
C15: 视觉物资 | D15: =SUMIF(支出流水表!$F$2:$F$479,分类统计!C15,支出流水表!$J$2:$J$479) -> 0
C16: 非官方成品模块 | D16: =SUMIF(支出流水表!$F$2:$F$479,分类统计!C16,支出流水表!$J$2:$J$479) -> 0
C17: 官方成品模块 | D17: =SUMIF(支出流水表!$F$2:$F$479,分类统计!C17,支出流水表!$J$2:$J$479) -> 0
C18: 运营宣传 | D18: =SUMIF(支出流水表!$F$2:$F$479,分类统计!C18,支出流水表!$J$2:$J$479) -> 0
C19: 实验室资产 | D19: =SUMIF(支出流水表!$F$2:$F$479,分类统计!C19,支出流水表!$J$2:$J$479) -> 0
C20: 差旅费 | D20: =SUMIF(支出流水表!$F$2:$F$479,分类统计!C20,支出流水表!$J$2:$J$479) -> 0
C21: 市内交通费 | D21: =SUMIF(支出流水表!$F$2:$F$479,分类统计!C21,支出流水表!$J$2:$J$479) -> 0
C22: 邮寄、物流费 | D22: =SUMIF(支出流水表!$F$2:$F$479,分类统计!C22,支出流水表!$J$2:$J$479) -> 0
C23: 其他 | D23: =SUMIF(支出流水表!$F$2:$F$479,分类统计!C23,支出流水表!$J$2:$J$479) -> 0
C24: 合计 | D24: =SUM(D2:D23) -> 0
